tldgen/__init__.py
tldgen/__main__.py
tldgen/version.py
tldgen-0.0.1.dist-info/LICENSE
tldgen-0.0.1.dist-info/METADATA
tldgen-0.0.1.dist-info/WHEEL
tldgen-0.0.1.dist-info/entry_points.txt
tldgen-0.0.1.dist-info/top_level.txt
tldgen-0.0.1.dist-info/RECORD
