Metadata-Version: 2.1
Name: tldgen
Version: 0.0.1
Summary: Append TLDs to subdomains
Home-page: https://gitlab.com/Zer1t0/tldgen
Author: Eloy Pérez González
Classifier: Programming Language :: Python :: 3
Classifier: License :: OSI Approved :: GNU General Public License v3 (GPLv3)
License-File: LICENSE
Requires-Dist: requests
Requires-Dist: bs4
Requires-Dist: pandas
